{
    "option": {
        "quest_平安京": {
            "type": "select",
            "label": "关卡",
            "default": "q七条四坊",
            "cases": [
                {
                    "name": "q七条四坊",
                    "label": "q七条四坊",
                    "pipeline_override": {
                        "平安京关卡导航": {
                            "next": "q七条四坊"
                        }
                    }
                },
                {
                    "name": "q七条二坊",
                    "label": "q七条二坊",
                    "pipeline_override": {
                        "平安京关卡导航": {
                            "next": "q七条二坊"
                        }
                    }
                },
                {
                    "name": "q六条大路",
                    "label": "q六条大路",
                    "pipeline_override": {
                        "平安京关卡导航": {
                            "next": "q六条大路"
                        }
                    }
                },
                {
                    "name": "q贵族宅邸",
                    "label": "q贵族宅邸",
                    "pipeline_override": {
                        "平安京关卡导航": {
                            "next": "q贵族宅邸"
                        }
                    }
                },
                {
                    "name": "q朱雀门",
                    "label": "q朱雀门",
                    "pipeline_override": {
                        "平安京关卡导航": {
                            "next": "q朱雀门"
                        }
                    }
                },
                {
                    "name": "q平安宫",
                    "label": "q平安宫",
                    "pipeline_override": {
                        "平安京关卡导航": {
                            "next": "q平安宫"
                        }
                    }
                },
                {
                    "name": "q朱雀大路",
                    "label": "q朱雀大路",
                    "pipeline_override": {
                        "平安京关卡导航": {
                            "next": "q朱雀大路"
                        }
                    }
                },
                {
                    "name": "q稻荷神社",
                    "label": "q稻荷神社",
                    "pipeline_override": {
                        "平安京关卡导航": {
                            "next": "q稻荷神社"
                        }
                    }
                },
                {
                    "name": "q大宫大路",
                    "label": "q大宫大路",
                    "pipeline_override": {
                        "平安京关卡导航": {
                            "next": "q大宫大路"
                        }
                    }
                },
                {
                    "name": "q赖光的宅邸",
                    "label": "q赖光的宅邸",
                    "pipeline_override": {
                        "平安京关卡导航": {
                            "next": "q赖光的宅邸"
                        }
                    }
                },
                {
                    "name": "q五条大桥",
                    "label": "q五条大桥",
                    "pipeline_override": {
                        "平安京关卡导航": {
                            "next": "q五条大桥"
                        }
                    }
                },
                {
                    "name": "q大江山",
                    "label": "q大江山",
                    "pipeline_override": {
                        "平安京关卡导航": {
                            "next": "q大江山"
                        }
                    }
                },
                {
                    "name": "q三条三坊",
                    "label": "q三条三坊",
                    "pipeline_override": {
                        "平安京关卡导航": {
                            "next": "q三条三坊"
                        }
                    }
                }
            ]
        }
    }
}